CHANGES.rst
LICENSE
MANIFEST
README.rst
setup.py
skipdict.c
skiplist.c
skiplist.h
tests.py
skipdict.egg-info/PKG-INFO
skipdict.egg-info/SOURCES.txt
skipdict.egg-info/dependency_links.txt
skipdict.egg-info/not-zip-safe
skipdict.egg-info/top_level.txt