Metadata-Version: 1.1
Name: skipdict
Version: 1.0
Summary: Python dictionary object permanently sorted by value.
Home-page: https://github.com/malthe/skipdict
Author: Malthe Borch
Author-email: mborch@gmail.com
License: BSD
Platform: UNKNOWN
Classifier: Development Status :: 4 - Beta
Classifier: Intended Audience :: Developers
Classifier: License :: OSI Approved :: MIT License
Classifier: Programming Language :: C
Classifier: Programming Language :: Python :: 2.7
Classifier: Programming Language :: Python :: 3.3
Classifier: Programming Language :: Python :: 3.4
Classifier: Topic :: Software Development :: Libraries :: Python Modules
